herec/__init__.py
herec-0.0.1.dist-info/LICENSE
herec-0.0.1.dist-info/WHEEL
herec-0.0.1.dist-info/METADATA
herec-0.0.1.dist-info/RECORD
